xcpcio/__init__.py
xcpcio/__version__.py
xcpcio/constants.py
xcpcio/types.py
xcpcio/api/__init__.py
xcpcio/api/client.py
xcpcio/api/models.py
xcpcio/app/clics_archiver.py
xcpcio/app/clics_server.py
xcpcio/app/clics_uploader.py
xcpcio/clics/__init__.py
xcpcio/clics/clics_api_client.py
xcpcio/clics/contest_archiver.py
xcpcio/clics/contest_uploader.py
xcpcio/clics/api_server/__init__.py
xcpcio/clics/api_server/app.py
xcpcio/clics/api_server/dependencies.py
xcpcio/clics/api_server/server.py
xcpcio/clics/api_server/routes/__init__.py
xcpcio/clics/api_server/routes/access.py
xcpcio/clics/api_server/routes/accounts.py
xcpcio/clics/api_server/routes/awards.py
xcpcio/clics/api_server/routes/clarifications.py
xcpcio/clics/api_server/routes/contests.py
xcpcio/clics/api_server/routes/general.py
xcpcio/clics/api_server/routes/groups.py
xcpcio/clics/api_server/routes/judgement_types.py
xcpcio/clics/api_server/routes/judgements.py
xcpcio/clics/api_server/routes/languages.py
xcpcio/clics/api_server/routes/organizations.py
xcpcio/clics/api_server/routes/problems.py
xcpcio/clics/api_server/routes/runs.py
xcpcio/clics/api_server/routes/submissions.py
xcpcio/clics/api_server/routes/teams.py
xcpcio/clics/api_server/services/__init__.py
xcpcio/clics/api_server/services/contest_service.py
xcpcio/clics/base/__init__.py
xcpcio/clics/base/types.py
xcpcio/clics/model/__init__.py
xcpcio/clics/model/model_2023_06/__init__.py
xcpcio/clics/model/model_2023_06/model.py
xcpcio/clics/reader/__init__.py
xcpcio/clics/reader/contest_package_reader.py
xcpcio/clics/reader/interface.py
xcpcio-0.84.0.dist-info/METADATA
xcpcio-0.84.0.dist-info/WHEEL
xcpcio-0.84.0.dist-info/entry_points.txt
xcpcio-0.84.0.dist-info/RECORD
